laim/__init__.py
laim/__main__.py
laim/_version.py
laim/laim.py
laim/log.py
laim/util.py
laim-1.2.0.data/data/LICENSE
tests/__init__.py
tests/conftest.py
tests/test_cli.py
tests/test_core.py
tests/test_log.py
tests/integration/__init__.py
tests/integration/test_handler.py
tests/integration/test_smtp.py
laim-1.2.0.dist-info/LICENSE
laim-1.2.0.dist-info/METADATA
laim-1.2.0.dist-info/WHEEL
laim-1.2.0.dist-info/entry_points.txt
laim-1.2.0.dist-info/top_level.txt
laim-1.2.0.dist-info/RECORD
