Metadata-Version: 2.2
Name: laim
Version: 1.2.0
Summary: Local SMTP helper
Home-page: https://github.com/thusoy/laim
Author: Tarjei Husøy
Author-email: git@thusoy.com
License: Hippocratic
Classifier: Development Status :: 5 - Production/Stable
Classifier: Intended Audience :: System Administrators
Classifier: License :: OSI Approved :: MIT License
Classifier: Programming Language :: Python
Classifier: Programming Language :: Python :: 3
Classifier: Programming Language :: Python :: 3.6
Classifier: Programming Language :: Python :: 3.7
Classifier: Programming Language :: Python :: 3.8
Classifier: Programming Language :: Python :: 3.9
Classifier: Topic :: Communications :: Email
Classifier: Topic :: System :: Monitoring
Classifier: Topic :: System :: Systems Administration
License-File: LICENSE
Requires-Dist: aiosmtpd
Requires-Dist: blinker
Requires-Dist: pyyaml
Requires-Dist: sdnotify
Requires-Dist: setproctitle
Dynamic: author
Dynamic: author-email
Dynamic: classifier
Dynamic: description
Dynamic: description-content-type
Dynamic: home-page
Dynamic: license
Dynamic: requires-dist
Dynamic: summary
